tosclib/__init__.py
tosclib/controls.py
tosclib/elements.py
tosclib/layout.py
tosclib/py.typed
tosclib/tosc.py
tosclib-0.3.5.dist-info/LICENSE
tosclib-0.3.5.dist-info/METADATA
tosclib-0.3.5.dist-info/WHEEL
tosclib-0.3.5.dist-info/top_level.txt
tosclib-0.3.5.dist-info/RECORD
