Metadata-Version: 2.1
Name: tosclib
Version: 0.3.5
Summary: Generate and edit Touch OSC .tosc files
Home-page: https://github.com/AlbertoV5/tosclib
Author: Alberto Valdez
Author-email: avq5ac1@gmail.com
Classifier: Programming Language :: Python :: 3
Classifier: License :: OSI Approved :: MIT License
Classifier: Operating System :: OS Independent
Requires-Python: >=3.10
License-File: LICENSE
Requires-Dist: lxml (>=4.9.0)
Requires-Dist: numpy (>=1.22.3)
